multipleinputs/__init__.py
multipleinputs-1.0.2.dist-info/LICENCE
multipleinputs-1.0.2.dist-info/METADATA
multipleinputs-1.0.2.dist-info/WHEEL
multipleinputs-1.0.2.dist-info/top_level.txt
multipleinputs-1.0.2.dist-info/RECORD
