Metadata-Version: 2.1
Name: multipleinputs
Version: 1.0.2
Summary: A Python package to get multiple inputs from console as array in required datatype
Home-page: UNKNOWN
Author: Himank Jain
Author-email: himank369123@gmail.com
License: MIT
Platform: UNKNOWN
Classifier: License :: OSI Approved :: MIT License
Classifier: Programming Language :: Python :: 3
Classifier: Programming Language :: Python :: 3.7
Requires-Dist: numpy
